metadata_dc/__init__.py
metadata_dc/metadata.py
ndpmetadata-0.8.dist-info/METADATA
ndpmetadata-0.8.dist-info/WHEEL
ndpmetadata-0.8.dist-info/top_level.txt
ndpmetadata-0.8.dist-info/RECORD
